file_operations/__init__.py
file_operations/file_operations.py
tests/__init__.py
tests/test_file_operations.py
file_operations-1.0.5.dist-info/METADATA
file_operations-1.0.5.dist-info/WHEEL
file_operations-1.0.5.dist-info/top_level.txt
file_operations-1.0.5.dist-info/RECORD
