Metadata-Version: 2.1
Name: file_operations
Version: 1.0.5
Summary: Simple API for performing file and directory operations
Home-page: http://pypi.python.org/pypi/file_operations/
Author: Algorithms Path
Author-email: support@algorithmspath.com
License: MIT
Platform: UNKNOWN
Classifier: License :: OSI Approved :: MIT License
Classifier: Programming Language :: Python :: 3
Classifier: Programming Language :: Python :: 3.7
Requires-Python: >=3
